ipfabric_nornir/__init__.py
ipfabric_nornir/plugins/__init__.py
ipfabric_nornir/plugins/inventory/__init__.py
ipfabric_nornir/plugins/inventory/ipfabric.py
ipfabric_nornir-1.0.5.dist-info/METADATA
ipfabric_nornir-1.0.5.dist-info/WHEEL
ipfabric_nornir-1.0.5.dist-info/entry_points.txt
ipfabric_nornir-1.0.5.dist-info/licenses/LICENSE
ipfabric_nornir-1.0.5.dist-info/RECORD
