Metadata-Version: 2.4
Name: ipfabric_nornir
Version: 1.0.5
Summary: IP Fabric Offical Plugin for nornir
License: Apache-2.0
License-File: LICENSE
Keywords: ipfabric,ip-fabric,community-fabric
Author: IP Fabric Solution Architecture
Author-email: solution.architecture@ipfabric.io
Requires-Python: >=3.8.1,<4.0.0
Classifier: License :: OSI Approved :: Apache Software License
Classifier: Programming Language :: Python :: 3
Classifier: Programming Language :: Python :: 3.9
Classifier: Programming Language :: Python :: 3.10
Classifier: Programming Language :: Python :: 3.11
Classifier: Programming Language :: Python :: 3.12
Classifier: Programming Language :: Python :: 3.13
Classifier: Programming Language :: Python :: 3.14
Provides-Extra: all
Provides-Extra: examples
Provides-Extra: napalm
Provides-Extra: netmiko
Requires-Dist: ipfabric (>=7.0.0,<8.0.0)
Requires-Dist: nornir (>=3.4.1,<4.0.0)
Requires-Dist: nornir-napalm (>=0.4.0,<0.5.0) ; extra == "all" or extra == "examples" or extra == "napalm"
Requires-Dist: nornir-netmiko (>=1.0.0,<2.0.0) ; extra == "all" or extra == "examples" or extra == "netmiko"
Requires-Dist: nornir-utils (>=0.2.0,<0.3.0) ; extra == "all" or extra == "examples"
Requires-Dist: tenacity (>=8.0,<10.0)
Project-URL: Changelog, https://gitlab.com/ip-fabric/integrations/ipfabric_nornir/-/blob/main/CHANGELOG.md
Project-URL: Homepage, https://gitlab.com/ip-fabric/integrations/ipfabric_nornir
Project-URL: IP Fabric, https://ipfabric.io/
Project-URL: Repository, https://gitlab.com/ip-fabric/integrations/ipfabric_nornir
